snadra/__init__.py
snadra/__main__.py
snadra/_typing.py
snadra/_utils.py
snadra/_core/__init__.py
snadra/_core/base.py
snadra/_core/parsers.py
snadra/_core/commands/__init__.py
snadra/_core/commands/exit.py
snadra/_core/commands/help.py
snadra-0.0a1.dist-info/LICENSE
snadra-0.0a1.dist-info/METADATA
snadra-0.0a1.dist-info/WHEEL
snadra-0.0a1.dist-info/top_level.txt
snadra-0.0a1.dist-info/RECORD
