Metadata-Version: 2.1
Name: snadra
Version: 0.0a1
Summary: Metasploit clone written in python.
Home-page: UNKNOWN
Author: Shahar Naveh
License: UNKNOWN
Project-URL: Source, https://github.com/ShaharNaveh/snadra
Project-URL: Tracker, https://github.com/ShaharNaveh/snadra/issues
Platform: UNKNOWN
Classifier: Development Status :: 1 - Planning
Classifier: Environment :: Console
Classifier: Intended Audience :: Developers
Classifier: Intended Audience :: Information Technology
Classifier: Programming Language :: Python :: 3
Classifier: Programming Language :: Python :: 3.7
Classifier: Programming Language :: Python :: 3.8
Classifier: Programming Language :: Python :: 3.9
Classifier: Topic :: Software Development :: Libraries :: Python Modules
Requires-Python: <4.0,>=3.7
Requires-Dist: prompt-toolkit
Requires-Dist: pygments
Requires-Dist: rich
